README.md
setup.py
pyjeol/__init__.py
pyjeol/vars.py
pyjeol.egg-info/PKG-INFO
pyjeol.egg-info/SOURCES.txt
pyjeol.egg-info/dependency_links.txt
pyjeol.egg-info/top_level.txt